{"entries":[],"headings":["definición-de-estadística","rol-de-la-estadística-en-el-pesamiento-crítico","parámetros-en-estadísticas","tipos-de-estadística","e-descriptiva","muestras-reperesentativas","consideraciones-de-la-estadísticas-descriptiva","m-tendencia-central","media-aritmética","mediana","moda","medidas-de-dispersión-y-variabilidad","rango","cuartiles-cuantiles-y-percentiles","rango-intercuartil-iqr","varianza","desviación-estándar","coeficiente-de-variación","índices-de-diversidad","shannon-wiener-diversity-index","shannon-wiener-evenness-index-índice-de-uniformidad","datos-con-una-dimensión-1d","datos-con-más-de-una-dimensión","fundamentos"],"options":{"chapter-id":"fundamentos","chapters":true}}